[
  {
    "millName": "RTM001",
    "latitude": 5.587366,
    "longitude": 8.133794,
    "p1Amount": 314.56,
    "numTransactions": 11,
    "p1PriceTon": 53400,
    "lastTransactionDate": "2023-10-04"
  },
  {
    "millName": "RTM002",
    "latitude": 5.546921,
    "longitude": 8.198576,
    "p1Amount": 752.23,
    "numTransactions": 26,
    "p1PriceTon": 49800,
    "lastTransactionDate": "2023-10-12"
  },
  {
    "millName": "RTM003",
    "latitude": 5.595743,
    "longitude": 8.162048,
    "p1Amount": 104.78,
    "numTransactions": 4,
    "p1PriceTon": 51600,
    "lastTransactionDate": "2023-10-22"
  },
  {
    "millName": "RTM004",
    "latitude": 5.609851,
    "longitude": 8.183427,
    "p1Amount": 456.32,
    "numTransactions": 17,
    "p1PriceTon": 58700,
    "lastTransactionDate": "2023-10-08"
  },
  {
    "millName": "RTM005",
    "latitude": 5.573189,
    "longitude": 8.147905,
    "p1Amount": 789.12,
    "numTransactions": 22,
    "p1PriceTon": 47200,
    "lastTransactionDate": "2023-10-18"
  },
  {
    "millName": "RTM006",
    "latitude": 5.602437,
    "longitude": 8.169316,
    "p1Amount": 231.45,
    "numTransactions": 8,
    "p1PriceTon": 52900,
    "lastTransactionDate": "2023-10-15"
  },
  {
    "millName": "RTM007",
    "latitude": 5.558674,
    "longitude": 8.184294,
    "p1Amount": 437.68,
    "numTransactions": 14,
    "p1PriceTon": 54300,
    "lastTransactionDate": "2023-10-01"
  },
  {
    "millName": "RTM008",
    "latitude": 5.591822,
    "longitude": 8.159382,
    "p1Amount": 625.89,
    "numTransactions": 19,
    "p1PriceTon": 51100,
    "lastTransactionDate": "2023-10-14"
  },
  {
    "millName": "RTM009",
    "latitude": 5.565274,
    "longitude": 8.174624,
    "p1Amount": 192.34,
    "numTransactions": 7,
    "p1PriceTon": 57400,
    "lastTransactionDate": "2023-10-09"
  },
  {
    "millName": "RTM010",
    "latitude": 5.615365,
    "longitude": 8.197041,
    "p1Amount": 478.92,
    "numTransactions": 15,
    "p1PriceTon": 49500,
    "lastTransactionDate": "2023-10-03"
  },
  {
    "millName": "RTM011",
    "latitude": 5.550187,
    "longitude": 8.191803,
    "p1Amount": 871.45,
    "numTransactions": 24,
    "p1PriceTon": 56800,
    "lastTransactionDate": "2023-10-19"
  },
  {
    "millName": "RTM012",
    "latitude": 5.605732,
    "longitude": 8.175063,
    "p1Amount": 329.67,
    "numTransactions": 10,
    "p1PriceTon": 52600,
    "lastTransactionDate": "2023-10-07"
  },
  {
    "millName": "RTM013",
    "latitude": 5.562578,
    "longitude": 8.180485,
    "p1Amount": 523.42,
    "numTransactions": 16,
    "p1PriceTon": 54100,
    "lastTransactionDate": "2023-10-11"
  },
  {
    "millName": "RTM014",
    "latitude": 5.620548,
    "longitude": 8.191607,
    "p1Amount": 411.89,
    "numTransactions": 13,
    "p1PriceTon": 50300,
    "lastTransactionDate": "2023-10-05"
  },
  {
    "millName": "RTM015",
    "latitude": 5.556432,
    "longitude": 8.187216,
    "p1Amount": 677.23,
    "numTransactions": 20,
    "p1PriceTon": 59400,
    "lastTransactionDate": "2023-10-13"
  },
  {
    "millName": "RTM016",
    "latitude": 5.611753,
    "longitude": 8.170392,
    "p1Amount": 236.78,
    "numTransactions": 9,
    "p1PriceTon": 53800,
    "lastTransactionDate": "2023-10-06"
  },
  {
    "millName": "RTM017",
    "latitude": 5.568842,
    "longitude": 8.176738,
    "p1Amount": 789.54,
    "numTransactions": 23,
    "p1PriceTon": 47900,
    "lastTransactionDate": "2023-10-17"
  },
  {
    "millName": "RTM018",
    "latitude": 5.603914,
    "longitude": 8.164074,
    "p1Amount": 451.23,
    "numTransactions": 14,
    "p1PriceTon": 55200,
    "lastTransactionDate": "2023-10-02"
  },
  {
    "millName": "RTM019",
    "latitude": 5.573542,
    "longitude": 8.182391,
    "p1Amount": 612.78,
    "numTransactions": 18,
    "p1PriceTon": 52500,
    "lastTransactionDate": "2023-10-10"
  },
  {
    "millName": "RTM020",
    "latitude": 5.617036,
    "longitude": 8.188724,
    "p1Amount": 298.45,
    "numTransactions": 10,
    "p1PriceTon": 54700,
    "lastTransactionDate": "2023-10-04"
  },
  {
    "millName": "RTM021",
    "latitude": 5.560843,
    "longitude": 8.190608,
    "p1Amount": 734.12,
    "numTransactions": 21,
    "p1PriceTon": 48600,
    "lastTransactionDate": "2023-10-12"
  },
  {
    "millName": "RTM022",
    "latitude": 5.608209,
    "longitude": 8.172581,
    "p1Amount": 402.67,
    "numTransactions": 13,
    "p1PriceTon": 53300,
    "lastTransactionDate": "2023-10-22"
  },
  {
    "millName": "RTM023",
    "latitude": 5.567458,
    "longitude": 8.178865,
    "p1Amount": 592.34,
    "numTransactions": 17,
    "p1PriceTon": 57100,
    "lastTransactionDate": "2023-10-08"
  },
  {
    "millName": "RTM024",
    "latitude": 5.613421,
    "longitude": 8.185229,
    "p1Amount": 471.89,
    "numTransactions": 15,
    "p1PriceTon": 50900,
    "lastTransactionDate": "2023-10-18"
  },
  {
    "millName": "RTM025",
    "latitude": 5.553126,
    "longitude": 8.192897,
    "p1Amount": 804.56,
    "numTransactions": 22,
    "p1PriceTon": 54600,
    "lastTransactionDate": "2023-10-15"
  },
  {
    "millName": "RTM026",
    "latitude": 5.605092,
    "longitude": 8.162753,
    "p1Amount": 297.23,
    "numTransactions": 10,
    "p1PriceTon": 52800,
    "lastTransactionDate": "2023-10-01"
  },
  {
    "millName": "RTM027",
    "latitude": 5.570387,
    "longitude": 8.180207,
    "p1Amount": 682.45,
    "numTransactions": 19,
    "p1PriceTon": 51400,
    "lastTransactionDate": "2023-10-14"
  },
  {
    "millName": "RTM028",
    "latitude": 5.611129,
    "longitude": 8.177595,
    "p1Amount": 238.12,
    "numTransactions": 8,
    "p1PriceTon": 57700,
    "lastTransactionDate": "2023-10-09"
  },
  {
    "millName": "RTM029",
    "latitude": 5.559632,
    "longitude": 8.188016,
    "p1Amount": 519.34,
    "numTransactions": 16,
    "p1PriceTon": 49200,
    "lastTransactionDate": "2023-10-03"
  },
  {
    "millName": "RTM030",
    "latitude": 5.614792,
    "longitude": 8.192825,
    "p1Amount": 767.89,
    "numTransactions": 21,
    "p1PriceTon": 57000,
    "lastTransactionDate": "2023-10-19"
  },
  {
    "millName": "RTM031",
    "latitude": 5.554278,
    "longitude": 8.185319,
    "p1Amount": 386.45,
    "numTransactions": 12,
    "p1PriceTon": 52400,
    "lastTransactionDate": "2023-10-07"
  },
  {
    "millName": "RTM032",
    "latitude": 5.609476,
    "longitude": 8.168937,
    "p1Amount": 621.78,
    "numTransactions": 18,
    "p1PriceTon": 53600,
    "lastTransactionDate": "2023-10-11"
  },
  {
    "millName": "RTM033",
    "latitude": 5.562165,
    "longitude": 8.184602,
    "p1Amount": 451.23,
    "numTransactions": 14,
    "p1PriceTon": 50000,
    "lastTransactionDate": "2023-10-05"
  },
  {
    "millName": "RTM034",
    "latitude": 5.616703,
    "longitude": 8.188119,
    "p1Amount": 719.45,
    "numTransactions": 20,
    "p1PriceTon": 59100,
    "lastTransactionDate": "2023-10-13"
  },
  {
    "millName": "RTM035",
    "latitude": 5.557598,
    "longitude": 8.190031,
    "p1Amount": 292.67,
    "numTransactions": 9,
    "p1PriceTon": 54000,
    "lastTransactionDate": "2023-10-06"
  },
  {
    "millName": "RTM036",
    "latitude": 5.612048,
    "longitude": 8.172408,
    "p1Amount": 836.24,
    "numTransactions": 23,
    "p1PriceTon": 48300,
    "lastTransactionDate": "2023-10-17"
  },
  {
    "millName": "RTM037",
    "latitude": 5.560105,
    "longitude": 8.186654,
    "p1Amount": 497.56,
    "numTransactions": 15,
    "p1PriceTon": 55500,
    "lastTransactionDate": "2023-10-02"
  },
  {
    "millName": "RTM038",
    "latitude": 5.617401,
    "longitude": 8.183809,
    "p1Amount": 669.23,
    "numTransactions": 19,
    "p1PriceTon": 52200,
    "lastTransactionDate": "2023-10-10"
  },
  {
    "millName": "RTM039",
    "latitude": 5.552168,
    "longitude": 8.193712,
    "p1Amount": 354.78,
    "numTransactions": 11,
    "p1PriceTon": 55000,
    "lastTransactionDate": "2023-10-04"
  },
  {
    "millName": "RTM040",
    "latitude": 5.609594,
    "longitude": 8.177257,
    "p1Amount": 781.45,
    "numTransactions": 22,
    "p1PriceTon": 48900,
    "lastTransactionDate": "2023-10-12"
  },
  {
    "millName": "RTM041",
    "latitude": 5.564713,
    "longitude": 8.183427,
    "p1Amount": 440.89,
    "numTransactions": 14,
    "p1PriceTon": 53900,
    "lastTransactionDate": "2023-10-22"
  },
  {
    "millName": "RTM042",
    "latitude": 5.613786,
    "longitude": 8.189715,
    "p1Amount": 625.34,
    "numTransactions": 18,
    "p1PriceTon": 56600,
    "lastTransactionDate": "2023-10-08"
  },
  {
    "millName": "RTM043",
    "latitude": 5.558431,
    "longitude": 8.191011,
    "p1Amount": 509.68,
    "numTransactions": 16,
    "p1PriceTon": 51300,
    "lastTransactionDate": "2023-10-18"
  },
  {
    "millName": "RTM044",
    "latitude": 5.615157,
    "longitude": 8.184644,
    "p1Amount": 743.23,
    "numTransactions": 21,
    "p1PriceTon": 55300,
    "lastTransactionDate": "2023-10-15"
  },
  {
    "millName": "RTM045",
    "latitude": 5.551784,
    "longitude": 8.195647,
    "p1Amount": 267.34,
    "numTransactions": 9,
    "p1PriceTon": 52700,
    "lastTransactionDate": "2023-10-01"
  },
  {
    "millName": "RTM046",
    "latitude": 5.607843,
    "longitude": 8.165928,
    "p1Amount": 893.12,
    "numTransactions": 25,
    "p1PriceTon": 51700,
    "lastTransactionDate": "2023-10-14"
  },
  {
    "millName": "RTM047",
    "latitude": 5.569247,
    "longitude": 8.179562,
    "p1Amount": 156.78,
    "numTransactions": 6,
    "p1PriceTon": 58200,
    "lastTransactionDate": "2023-10-09"
  },
  {
    "millName": "RTM048",
    "latitude": 5.618925,
    "longitude": 8.186573,
    "p1Amount": 545.67,
    "numTransactions": 17,
    "p1PriceTon": 49900,
    "lastTransactionDate": "2023-10-03"
  },
  {
    "millName": "RTM049",
    "latitude": 5.556123,
    "longitude": 8.194283,
    "p1Amount": 712.45,
    "numTransactions": 20,
    "p1PriceTon": 56400,
    "lastTransactionDate": "2023-10-19"
  },
  {
    "millName": "RTM050",
    "latitude": 5.610867,
    "longitude": 8.171645,
    "p1Amount": 423.89,
    "numTransactions": 13,
    "p1PriceTon": 53100,
    "lastTransactionDate": "2023-10-07"
  }
]